technical_indicator/__init__.py
technical_indicator/momentum/__init__.py
technical_indicator/momentum/calculate_macd.py
technical_indicator/momentum/calculate_macd_histogram.py
technical_indicator/momentum/calculate_momentum.py
technical_indicator/momentum/calculate_rsi.py
technical_indicator/trend/__init__.py
technical_indicator/trend/calculate_moving_average.py
technical_indicator/volume/__init__.py
technical_indicator/volume/calculate_on_balance_volume.py
technical_indicator/volume/calculate_volume_weighted_average_price.py
technical_indicator-1.0.3.dist-info/LICENSE
technical_indicator-1.0.3.dist-info/METADATA
technical_indicator-1.0.3.dist-info/WHEEL
technical_indicator-1.0.3.dist-info/top_level.txt
technical_indicator-1.0.3.dist-info/RECORD
