Metadata-Version: 2.1
Name: technical-indicator
Version: 1.0.3
Summary: Technical Indicator is a Python package for calculating technical indicators from financial time series datasets
Home-page: https://github.com/nguyentruonglong/technical-indicator
Author: Nguyen Truong Long
Author-email: contact@nguyentruonglong.com
License: UNKNOWN
Project-URL: Bug Tracker, https://github.com/nguyentruonglong/technical-indicator/issues
Platform: UNKNOWN
Classifier: Programming Language :: Python :: 3
Classifier: License :: OSI Approved :: GNU General Public License v3 or later (GPLv3+)
Classifier: Operating System :: OS Independent
Classifier: Programming Language :: Python :: 3
Classifier: Programming Language :: Python :: 3.5
Classifier: Programming Language :: Python :: 3.6
Classifier: Programming Language :: Python :: 3.7
Classifier: Programming Language :: Python :: 3.8
Classifier: Programming Language :: Python :: 3.9
Requires-Python: >=3.5.3
License-File: LICENSE
Requires-Dist: pandas
Requires-Dist: numpy
Provides-Extra: test
Requires-Dist: pytest ; extra == 'test'
